cs_robots/apps.py
cs_robots/forms.py
cs_robots/urls.py
cs_robots/views.py
cs_robots/templates/cs_robots/edit_cs_robots.html
cs_robots/templates/cs_robots/admin/index.html
cs_robots/tests/__init__.py
cs_robots/tests/test_forms.py
cs_robots/tests/test_views.py
django_cs_robots-1.0.2.dist-info/licenses/LICENSE
django_cs_robots-1.0.2.dist-info/METADATA
django_cs_robots-1.0.2.dist-info/WHEEL
django_cs_robots-1.0.2.dist-info/top_level.txt
django_cs_robots-1.0.2.dist-info/RECORD
