Metadata-Version: 2.4
Name: django-cs-robots
Version: 1.0.2
Summary: A django app to change robots.txt from the admin panel without using the database.
Author-email: Jatsu Argarate <jargarae@codesyntax.com>
License: MIT License
Project-URL: Homepage, https://github.com/jatsu/django-cs-robots
Project-URL: Issues, https://github.com/jatsu/django-cs-robots/issues
Classifier: Environment :: Web Environment
Classifier: Framework :: Django
Classifier: Framework :: Django :: 4.2
Classifier: Framework :: Django :: 5.2
Classifier: Framework :: Django :: 6.0
Classifier: Intended Audience :: Developers
Classifier: License :: OSI Approved :: MIT License
Classifier: Operating System :: OS Independent
Classifier: Programming Language :: Python
Classifier: Programming Language :: Python :: 3
Classifier: Programming Language :: Python :: 3.9
Classifier: Programming Language :: Python :: 3.10
Classifier: Programming Language :: Python :: 3.11
Classifier: Programming Language :: Python :: 3.12
Classifier: Programming Language :: Python :: 3.13
Requires-Python: >=3.9
License-File: LICENSE
Requires-Dist: Django>=3.2
Dynamic: license-file
